FunctionalSubgraph/__init__.py
FunctionalSubgraph/nmf.py
FunctionalSubgraph/optimize.py
FunctionalSubgraph/Common/__init__.py
FunctionalSubgraph/Common/display.py
FunctionalSubgraph/Common/errors.py
FunctionalSubgraph/Utils/__init__.py
FunctionalSubgraph/Utils/matrix_utils.py
FunctionalSubgraph/Utils/nnls.py
FunctionalSubgraph-1.0.0.post10.dist-info/DESCRIPTION.rst
FunctionalSubgraph-1.0.0.post10.dist-info/METADATA
FunctionalSubgraph-1.0.0.post10.dist-info/RECORD
FunctionalSubgraph-1.0.0.post10.dist-info/WHEEL
FunctionalSubgraph-1.0.0.post10.dist-info/metadata.json
FunctionalSubgraph-1.0.0.post10.dist-info/top_level.txt
