Metadata-Version: 2.0
Name: FunctionalSubgraph
Version: 1.0.0.post10
Summary: FunctionalSubgraph: An ML tool for dynamic graph analysis.
Home-page: UNKNOWN
Author: Ankit N. Khambhati
Author-email: akhambhati@gmail.com
License: UNKNOWN
Platform: UNKNOWN
Classifier: Development Status :: 4 - Beta
Classifier: Intended Audience :: Science/Research
Classifier: Topic :: Software Development :: Build Tools
Classifier: License :: OSI Approved :: Nokia Open Source License
Classifier: Natural Language :: English
Classifier: Programming Language :: Python :: 2.7
Classifier: Programming Language :: Python :: 3.6
Requires-Dist: numpy
Requires-Dist: scipy
Requires-Dist: ipython
